proxmox_cloud_importer/__init__.py
proxmox_cloud_importer/cli.py
proxmox_cloud_importer/config.py
proxmox_cloud_importer/importer.py
proxmox_cloud_importer/logging_config.py
proxmox_cloud_importer/resources/images.yaml
proxmox_cloud_importer-0.1.7.data/data/proxmox_cloud_importer/resources/images.yaml
proxmox_cloud_importer-0.1.7.dist-info/METADATA
proxmox_cloud_importer-0.1.7.dist-info/WHEEL
proxmox_cloud_importer-0.1.7.dist-info/entry_points.txt
proxmox_cloud_importer-0.1.7.dist-info/licenses/LICENSE
proxmox_cloud_importer-0.1.7.dist-info/RECORD
