Metadata-Version: 2.4
Name: proxmox-cloud-importer
Version: 0.1.7
Summary: CLI tool for importing cloud images to Proxmox server
Project-URL: Homepage, https://github.com/yurzs/proxmox-cloud-importer
Project-URL: Repository, https://github.com/yurzs/proxmox-cloud-importer
Project-URL: Issues, https://github.com/yurzs/proxmox-cloud-importer/issues
Author-email: Yury Sokov <me@yurzs.dev>
License: MIT License
License-File: LICENSE
Keywords: cli,cloud,images,proxmox
Classifier: Development Status :: 3 - Alpha
Classifier: Intended Audience :: System Administrators
Classifier: License :: OSI Approved :: MIT License
Classifier: Programming Language :: Python :: 3
Classifier: Programming Language :: Python :: 3.8
Classifier: Programming Language :: Python :: 3.9
Classifier: Programming Language :: Python :: 3.10
Classifier: Programming Language :: Python :: 3.11
Classifier: Programming Language :: Python :: 3.12
Requires-Python: >=3.8
Requires-Dist: click>=8.0.0
Requires-Dist: plumbum>=1.8.0
Requires-Dist: pyyaml>=6.0
Requires-Dist: requests>=2.28.0
Requires-Dist: rich>=13.0.0
Provides-Extra: dev
Requires-Dist: black>=22.0.0; extra == 'dev'
Requires-Dist: flake8>=5.0.0; extra == 'dev'
Requires-Dist: mypy>=1.0.0; extra == 'dev'
Requires-Dist: pytest-cov>=4.0.0; extra == 'dev'
Requires-Dist: pytest>=7.0.0; extra == 'dev'
